wrdice/Army.py
wrdice/Battle.py
wrdice/D12Colored.py
wrdice/QuickBattle.py
wrdice/Simulate.py
wrdice/__init__.py
wrdice/__main__.py
wrdice/config.py
wrdice/util.py
WRDice-0.0.1.17.dist-info/METADATA
WRDice-0.0.1.17.dist-info/WHEEL
WRDice-0.0.1.17.dist-info/top_level.txt
WRDice-0.0.1.17.dist-info/RECORD
